requestsgcp/__init__.py
requestsgcp/requests.py
requestsgcp/version.py
requests_gcp-0.2.0.dist-info/LICENSE
requests_gcp-0.2.0.dist-info/METADATA
requests_gcp-0.2.0.dist-info/WHEEL
requests_gcp-0.2.0.dist-info/top_level.txt
requests_gcp-0.2.0.dist-info/RECORD
