Metadata-Version: 2.1
Name: requests-gcp
Version: 0.2.0
Summary: Python requests wrapper for service-to-service auth on GCP
Home-page: https://github.com/adrianchifor/requests-gcp
Author: Adrian Chifor
Author-email: me@adrianchifor.com
License: Apache License 2.0
Keywords: requests gcp wrapper
Platform: UNKNOWN
Classifier: Development Status :: 4 - Beta
Classifier: Intended Audience :: Developers
Classifier: Topic :: Software Development :: Libraries :: Python Modules
Classifier: License :: OSI Approved :: Apache Software License
Classifier: Programming Language :: Python :: 3.6
Classifier: Programming Language :: Python :: 3.7
Classifier: Programming Language :: Python :: 3.8
Requires-Python: >=3.6
Requires-Dist: requests (>=2.23.0)
